MANIFEST.in
README.md
requirements.txt
setup.py
genderizer/__init__.py
genderizer/cachedModel.py
genderizer/genderizer.py
genderizer/memcachedNamesCollection.py
genderizer/mongoNamesCollection.py
genderizer/namesCollection.py
genderizer.egg-info/PKG-INFO
genderizer.egg-info/SOURCES.txt
genderizer.egg-info/dependency_links.txt
genderizer.egg-info/top_level.txt
genderizer/data/__init__.py
genderizer/data/model_en.txt
genderizer/data/model_generator.py
genderizer/data/model_tr.txt
genderizer/data/name_gender.csv