Metadata-Version: 1.0
Name: genderizer
Version: 0.1.2.3
Summary: Genderizer tries to infer gender information looking at first name and/or making text analysis
Home-page: https://github.com/muatik/genderizer
Author: Mustafa Atik
Author-email: muatik@gmail.com
License: MIT
Platform: any
